{"id": 54164, "name": "VELO Mini Crispy Peppermint 3", "history": [{"timestamp": "2026-05-01T15:30:59.245015", "stock": 10, "price": 990.0}, {"timestamp": "2026-05-01T16:42:44.352882", "stock": 10, "price": 990.0}, {"timestamp": "2026-05-01T17:46:58.490177", "stock": 10, "price": 990.0}, {"timestamp": "2026-05-01T18:54:28.466631", "stock": 10, "price": 990.0}, {"timestamp": "2026-05-01T19:59:26.258595", "stock": 5, "price": 990.0}, {"timestamp": "2026-05-01T20:51:32.232739", "stock": 5, "price": 990.0}, {"timestamp": "2026-05-01T21:41:55.804483", "stock": 5, "price": 990.0}, {"timestamp": "2026-05-02T11:36:37.794050", "stock": 5, "price": 990.0}, {"timestamp": "2026-05-02T12:41:46.599513", "stock": 5, "price": 990.0}, {"timestamp": "2026-05-02T14:04:24.176362", "stock": 5, "price": 990.0}, {"timestamp": "2026-05-02T15:09:23.075658", "stock": 5, "price": 990.0}, {"timestamp": "2026-05-02T16:05:32.788150", "stock": 5, "price": 990.0}, {"timestamp": "2026-05-02T17:11:00.703846", "stock": 5, "price": 990.0}, {"timestamp": "2026-05-02T18:06:24.027895", "stock": 5, "price": 990.0}, {"timestamp": "2026-05-02T19:31:50.981555", "stock": 5, "price": 990.0}, {"timestamp": "2026-05-02T20:29:55.696780", "stock": 5, "price": 990.0}, {"timestamp": "2026-05-02T21:08:28.882476", "stock": 5, "price": 990.0}, {"timestamp": "2026-05-02T22:04:11.712600", "stock": 5, "price": 990.0}, {"timestamp": "2026-05-03T11:34:29.937587", "stock": 5, "price": 990.0}, {"timestamp": "2026-05-03T12:41:11.458907", "stock": 5, "price": 990.0}, {"timestamp": "2026-05-03T14:04:41.785860", "stock": 5, "price": 990.0}, {"timestamp": "2026-05-03T15:10:03.860950", "stock": 5, "price": 990.0}, {"timestamp": "2026-05-03T16:05:50.860657", "stock": 5, "price": 990.0}, {"timestamp": "2026-05-03T17:13:02.403272", "stock": 5, "price": 990.0}, {"timestamp": "2026-05-03T18:07:48.358093", "stock": 5, "price": 990.0}, {"timestamp": "2026-05-03T19:31:34.831151", "stock": 5, "price": 990.0}, {"timestamp": "2026-05-03T20:31:05.485591", "stock": 5, "price": 990.0}, {"timestamp": "2026-05-03T21:31:26.945778", "stock": 5, "price": 990.0}, {"timestamp": "2026-05-04T12:16:58.805748", "stock": 5, "price": 990.0}, {"timestamp": "2026-05-04T14:35:58.224822", "stock": 5, "price": 990.0}, {"timestamp": "2026-05-04T16:25:26.228536", "stock": 5, "price": 990.0}, {"timestamp": "2026-05-04T17:57:24.811014", "stock": 5, "price": 990.0}, {"timestamp": "2026-05-04T19:17:55.360210", "stock": 4, "price": 990.0}, {"timestamp": "2026-05-04T20:44:26.781594", "stock": 4, "price": 990.0}, {"timestamp": "2026-05-04T21:51:48.122659", "stock": 4, "price": 990.0}, {"timestamp": "2026-05-05T11:54:39.820028", "stock": 4, "price": 990.0}, {"timestamp": "2026-05-05T13:05:50.647774", "stock": 4, "price": 990.0}, {"timestamp": "2026-05-05T17:00:47.815970", "stock": 4, "price": 990.0}, {"timestamp": "2026-05-05T18:12:23.159285", "stock": 4, "price": 990.0}, {"timestamp": "2026-05-05T19:56:34.671245", "stock": 4, "price": 990.0}, {"timestamp": "2026-05-05T20:53:45.678934", "stock": 4, "price": 990.0}, {"timestamp": "2026-05-05T21:51:22.675277", "stock": 4, "price": 990.0}, {"timestamp": "2026-05-06T12:22:27.286749", "stock": 4, "price": 990.0}, {"timestamp": "2026-05-06T15:07:39.475121", "stock": 4, "price": 990.0}, {"timestamp": "2026-05-06T16:57:57.506657", "stock": 4, "price": 990.0}, {"timestamp": "2026-05-06T18:12:11.552094", "stock": 4, "price": 990.0}, {"timestamp": "2026-05-06T20:06:28.622330", "stock": 4, "price": 990.0}, {"timestamp": "2026-05-06T21:36:19.871651", "stock": 4, "price": 990.0}, {"timestamp": "2026-05-07T12:24:03.344784", "stock": 4, "price": 990.0}, {"timestamp": "2026-05-07T15:09:33.589432", "stock": 4, "price": 990.0}, {"timestamp": "2026-05-07T17:13:30.985390", "stock": 4, "price": 990.0}, {"timestamp": "2026-05-07T19:10:20.007580", "stock": 4, "price": 990.0}, {"timestamp": "2026-05-07T20:45:22.974188", "stock": 4, "price": 990.0}, {"timestamp": "2026-05-07T21:44:58.108419", "stock": 4, "price": 990.0}, {"timestamp": "2026-05-08T12:03:45.661091", "stock": 4, "price": 990.0}, {"timestamp": "2026-05-08T14:20:48.082083", "stock": 4, "price": 990.0}, {"timestamp": "2026-05-08T15:57:08.605716", "stock": 4, "price": 990.0}, {"timestamp": "2026-05-08T17:04:19.726587", "stock": 4, "price": 990.0}, {"timestamp": "2026-05-08T18:49:58.545688", "stock": 4, "price": 990.0}, {"timestamp": "2026-05-08T20:02:35.714903", "stock": 4, "price": 990.0}]}